pyplayground/__init__.py
pyplayground/game.py
pyplayground_ralfeus-0.0.1.dist-info/LICENSE
pyplayground_ralfeus-0.0.1.dist-info/METADATA
pyplayground_ralfeus-0.0.1.dist-info/WHEEL
pyplayground_ralfeus-0.0.1.dist-info/top_level.txt
pyplayground_ralfeus-0.0.1.dist-info/RECORD
