Metadata-Version: 2.1
Name: pyplayground-ralfeus
Version: 0.0.1
Summary: Module to create simple games using pygame
Home-page: https://github.com/ralfeus/pyplayground
Author: Mychajlo Chodorev
Author-email: ralfeus@gmail.com
License: UNKNOWN
Platform: UNKNOWN
Classifier: Programming Language :: Python :: 3
Classifier: License :: OSI Approved :: MIT License
Classifier: Operating System :: OS Independent
Requires-Python: >=3.6
Requires-Dist: numpy
Requires-Dist: pygame
